bundecto/__init__.py
bundecto/__main__.py
bundecto/editor.py
bundecto-1.1.dist-info/licenses/LICENSE
bundecto-1.1.dist-info/METADATA
bundecto-1.1.dist-info/WHEEL
bundecto-1.1.dist-info/entry_points.txt
bundecto-1.1.dist-info/top_level.txt
bundecto-1.1.dist-info/RECORD
