Metadata-Version: 2.4
Name: bundecto
Version: 1.1
Summary: A minimal terminal text editor with a curses-based UI
Author-email: voyager-2021 <voyager-2019@outlook.com>
License: MIT
Project-URL: Homepage, https://github.com/voyager-2021/bundecto
Project-URL: Issues, https://github.com/voyager-2021/bundecto/issues
Keywords: text-editor,terminal,curses,editor
Classifier: Development Status :: 3 - Alpha
Classifier: Environment :: Console
Classifier: Intended Audience :: Developers
Classifier: License :: OSI Approved :: MIT License
Classifier: Operating System :: POSIX
Classifier: Programming Language :: Python :: 3
Classifier: Topic :: Text Editors
Classifier: Topic :: Software Development :: Libraries :: Python Modules
Requires-Python: >=3.8
License-File: LICENSE
Dynamic: license-file
